pytest_jtr/__init__.py
pytest_jtr/plugin.py
pytest_jtr/serialize.py
pytest_jtr-1.4.0.dist-info/LICENSE
pytest_jtr-1.4.0.dist-info/WHEEL
pytest_jtr-1.4.0.dist-info/entry_points.txt
pytest_jtr-1.4.0.dist-info/METADATA
pytest_jtr-1.4.0.dist-info/RECORD
