Metadata-Version: 2.1
Name: pytest-jtr
Version: 1.4.0
Summary: pytest plugin supporting json test report output
License: MIT
Keywords: test,pytest,json,report
Author: Gleams API user
Author-email: Stephen.Swannell+ghapi@gmail.com
Requires-Python: >=3.8.1,<3.13.0
Classifier: License :: OSI Approved :: MIT License
Classifier: Programming Language :: Python :: 3
Classifier: Programming Language :: Python :: 3.9
Classifier: Programming Language :: Python :: 3.10
Classifier: Programming Language :: Python :: 3.11
Requires-Dist: fire (>=0.4.0,<0.5.0)
Requires-Dist: jinja2 (>3.1.2)
Requires-Dist: loguru (>=0.6.0,<0.7.0)
Requires-Dist: pytest (>=7.1.2,<8.0.0)
Requires-Dist: pytest-metadata (>=2.0.1,<3.0.0)
Requires-Dist: pytest-xdist (>=2.5.0,<3.0.0)
Requires-Dist: rich (>=13.3.0,<14.0.0)
Requires-Dist: wheel (>0.37.1)
